{
    "drug_name": "Colorescience Total Protection No Show Mineral Sunscreen",
    "generic_name": [
        "ZINC OXIDE"
    ],
    "active_ingredients": [
        "Colorescience Total Protection No Show Mineral Sunscreen Active Ingredients"
    ],
    "indications_and_usage": [
        "Colorescience Total Protection No Show Mineral Sunscreen Indications & usage"
    ],
    "contraindications": [],
    "boxed_warning": [],
    "warnings_and_cautions": [],
    "adverse_reactions": [],
    "drug_interactions": [],
    "dosage_and_administration": [
        "Colorescience Total Protection No Show Mineral Sunscreen Dosage and Administration"
    ],
    "overdosage": []
}