{
    "drug_name": "ANTACID",
    "generic_name": [
        "CALCIUM CARBONATE"
    ],
    "active_ingredients": [
        "Active Ingredient (in each tablet) Calcium Carbonate 10 gr (648 mg)"
    ],
    "indications_and_usage": [
        "Uses relieves acid indigestion heartburn sour stomach upset stomach associated with these symptoms"
    ],
    "contraindications": [],
    "boxed_warning": [],
    "warnings_and_cautions": [],
    "adverse_reactions": [],
    "drug_interactions": [],
    "dosage_and_administration": [
        "Directions take one to four tablets daily. do not take more than 4 tablets in 24 hours do not use the maximum dosage for more than 2 weeks"
    ],
    "overdosage": []
}